kraken_testdata/kraken_testdata.py
kraken_testdata-0.0.6.dist-info/LICENSE.txt
kraken_testdata-0.0.6.dist-info/METADATA
kraken_testdata-0.0.6.dist-info/WHEEL
kraken_testdata-0.0.6.dist-info/top_level.txt
kraken_testdata-0.0.6.dist-info/RECORD
